{
  "main": {
    "id": "c1c1ce69f90fc23e",
    "type": "split",
    "children": [
      {
        "id": "fb349c4e9f1b5265",
        "type": "tabs",
        "children": [
          {
            "id": "16c69b9e1d1200aa",
            "type": "leaf",
            "state": {
              "type": "markdown",
              "state": {
                "file": "C++/Type Aliases.md",
                "mode": "preview",
                "source": true
              }
            }
          },
          {
            "id": "56a643767af9c348",
            "type": "leaf",
            "state": {
              "type": "markdown",
              "state": {
                "file": "C++/STL/valarray/min.md",
                "mode": "source",
                "source": true
              }
            }
          }
        ]
      }
    ],
    "direction": "vertical"
  },
  "left": {
    "id": "8f40538da6a96471",
    "type": "split",
    "children": [
      {
        "id": "2f602f09e075276b",
        "type": "tabs",
        "children": [
          {
            "id": "906761a8f911bb3b",
            "type": "leaf",
            "state": {
              "type": "file-explorer",
              "state": {
                "sortOrder": "alphabetical"
              }
            }
          },
          {
            "id": "808f427b7585f066",
            "type": "leaf",
            "state": {
              "type": "search",
              "state": {
                "query": "struc",
                "matchingCase": false,
                "explainSearch": false,
                "collapseAll": false,
                "extraContext": false,
                "sortOrder": "alphabetical"
              }
            }
          },
          {
            "id": "7c3426a7a1319654",
            "type": "leaf",
            "state": {
              "type": "bookmarks",
              "state": {}
            }
          }
        ]
      }
    ],
    "direction": "horizontal",
    "width": 300
  },
  "right": {
    "id": "724c6b05ee31144f",
    "type": "split",
    "children": [
      {
        "id": "a2d8c6bbfa0103b0",
        "type": "tabs",
        "children": [
          {
            "id": "46fb9d4aa297dadd",
            "type": "leaf",
            "state": {
              "type": "backlink",
              "state": {
                "file": "C++/Type Aliases.md",
                "collapseAll": false,
                "extraContext": false,
                "sortOrder": "alphabetical",
                "showSearch": false,
                "searchQuery": "",
                "backlinkCollapsed": false,
                "unlinkedCollapsed": true
              }
            }
          },
          {
            "id": "639e7d16189edf0e",
            "type": "leaf",
            "state": {
              "type": "outgoing-link",
              "state": {
                "file": "C++/Type Aliases.md",
                "linksCollapsed": false,
                "unlinkedCollapsed": true
              }
            }
          },
          {
            "id": "1e42e8786131721c",
            "type": "leaf",
            "state": {
              "type": "tag",
              "state": {
                "sortOrder": "frequency",
                "useHierarchy": true
              }
            }
          },
          {
            "id": "77072313f4dd6845",
            "type": "leaf",
            "state": {
              "type": "outline",
              "state": {
                "file": "C++/Type Aliases.md"
              }
            }
          }
        ]
      }
    ],
    "direction": "horizontal",
    "width": 300,
    "collapsed": true
  },
  "left-ribbon": {
    "hiddenItems": {
      "switcher:Open quick switcher": false,
      "graph:Open graph view": false,
      "canvas:Create new canvas": false,
      "daily-notes:Open today's daily note": false,
      "templates:Insert template": false,
      "command-palette:Open command palette": false
    }
  },
  "active": "906761a8f911bb3b",
  "lastOpenFiles": [
    "C++/Macros.md",
    "C++/extern.md",
    "C++/Friend.md",
    "C++/Type Aliases.md",
    "C++/OOP/Static Class Member.md",
    "C++/Static Class Member.md",
    "C++/STL/<algorithm>/reverse.md",
    "C++/STL/<cstdlib>",
    "C++/STL/<numeric>",
    "C++/STL/<utility>",
    "C++/STL/Untitled.md",
    "C++/STL/<algorithm>/find.md",
    "C++/STL/<algorithm>/max.md",
    "C++/STL/valarray/sum.md",
    "C++/STL/valarray/size.md",
    "C++/STL/valarray/min.md",
    "C++/STL/valarray/max.md",
    "C++/STL/<numeric>/accumulate.md",
    "C++/STL/<cstdlib>/rand.md",
    "C++/STL/<utility>/pair.md",
    "C++/STL/<algorithm>/for_each.md",
    "C++/STL/<algorithm>/sort.md",
    "C++/STL/<algorithm>",
    "C++/STL/<algorithm>.md",
    "C++/Data Types/Compound Types/C-Style String/strncpy.md",
    "C++/Data Types/Compound Types/Enumerations/Overview.md",
    "C++/STL/valarray/Untitled",
    "C++/STL/valarray",
    "Pasted image 20240831114746.png",
    "C++/Data Types/Compound Types/Unions/00.md",
    "C++/Data Types/Compound Types/Enumerations",
    "C++/Data Types/Compound Types/Enumerations.md",
    "C++/Data Types/Compound Types/Structures/00.md",
    "C++/Data Types/Compound Types/Unions",
    "C++/Data Types/Compound Types/Structures/Struct Template.md",
    "C++/Operator",
    "C++/Variables/Fundamental Types/long",
    "screenshots/Screenshot 2024-08-15 at 9.28.08 AM.png",
    "screenshots/Screenshot 2024-08-09 at 11.04.37 AM.png",
    "screenshots/Screenshot 2024-08-15 at 4.48.48 PM.png",
    "screenshots/Screenshot 2024-08-06 at 12.28.50 PM.png",
    "screenshots/Screenshot 2024-08-04 at 7.38.57 PM.png",
    "screenshots/Screenshot 2024-08-04 at 3.10.44 PM.png",
    "screenshots/Screenshot 2024-08-04 at 3.10.20 PM.png",
    "screenshots/Screenshot 2024-08-03 at 3.05.51 PM.png",
    "screenshots/Screenshot 2024-08-01 at 11.09.03 AM.png",
    "Unity.canvas",
    "C++.canvas"
  ]
}